{
  "v": "5.7.4",
  "fr": 30,
  "ip": 0,
  "op": 120,
  "w": 1920,
  "h": 1080,
  "nm": "Homepage Scroll Animation",
  "ddd": 0,
  "assets": [],
  "layers": [
    {
      "ddd": 0,
      "ind": 1,
      "ty": 4,
      "nm": "Center Circle",
      "sr": 1,
      "ks": {
        "o": { "a": 1, "k": [
          { "t": 0, "s": [0], "e": [100] },
          { "t": 20, "s": [100], "e": [100] },
          { "t": 100, "s": [100], "e": [0] },
          { "t": 120, "s": [0] }
        ]},
        "r": { "a": 0, "k": 0 },
        "p": { "a": 0, "k": [960, 540, 0] },
        "a": { "a": 0, "k": [0, 0, 0] },
        "s": { "a": 1, "k": [
          { "t": 0, "s": [0, 0, 100], "e": [100, 100, 100] },
          { "t": 30, "s": [100, 100, 100], "e": [130, 130, 100] },
          { "t": 90, "s": [130, 130, 100], "e": [150, 150, 100] },
          { "t": 120, "s": [150, 150, 100] }
        ]}
      },
      "ao": 0,
      "shapes": [
        {
          "ty": "el",
          "d": 1,
          "s": { "a": 0, "k": [500, 500] },
          "p": { "a": 0, "k": [0, 0] },
          "nm": "Circle"
        },
        {
          "ty": "st",
          "c": { "a": 1, "k": [
            { "t": 0, "s": [0.984, 0.69, 0.494, 1], "e": [0.208, 0.506, 0.722, 1] },
            { "t": 60, "s": [0.208, 0.506, 0.722, 1], "e": [0.984, 0.69, 0.494, 1] },
            { "t": 120, "s": [0.984, 0.69, 0.494, 1] }
          ]},
          "o": { "a": 0, "k": 100 },
          "w": { "a": 1, "k": [
            { "t": 0, "s": [8], "e": [2] },
            { "t": 120, "s": [2] }
          ]},
          "lc": 2,
          "lj": 2,
          "nm": "Stroke"
        },
        {
          "ty": "fl",
          "c": { "a": 0, "k": [0.984, 0.69, 0.494, 0.05] },
          "o": { "a": 0, "k": 20 },
          "r": 1,
          "nm": "Fill"
        }
      ],
      "ip": 0,
      "op": 120,
      "st": 0
    },
    {
      "ddd": 0,
      "ind": 2,
      "ty": 4,
      "nm": "Rotating Square",
      "sr": 1,
      "ks": {
        "o": { "a": 1, "k": [
          { "t": 10, "s": [0], "e": [80] },
          { "t": 30, "s": [80], "e": [80] },
          { "t": 100, "s": [80], "e": [0] },
          { "t": 120, "s": [0] }
        ]},
        "r": { "a": 1, "k": [
          { "t": 0, "s": [0], "e": [180] },
          { "t": 120, "s": [180] }
        ]},
        "p": { "a": 1, "k": [
          { "t": 0, "s": [700, 350, 0], "e": [750, 300, 0] },
          { "t": 60, "s": [750, 300, 0], "e": [700, 350, 0] },
          { "t": 120, "s": [700, 350, 0] }
        ]},
        "a": { "a": 0, "k": [0, 0, 0] },
        "s": { "a": 1, "k": [
          { "t": 10, "s": [0, 0, 100], "e": [100, 100, 100] },
          { "t": 40, "s": [100, 100, 100] }
        ]}
      },
      "ao": 0,
      "shapes": [
        {
          "ty": "rc",
          "d": 1,
          "s": { "a": 0, "k": [100, 100] },
          "p": { "a": 0, "k": [0, 0] },
          "r": { "a": 0, "k": 0 },
          "nm": "Square"
        },
        {
          "ty": "fl",
          "c": { "a": 0, "k": [0.208, 0.506, 0.722, 1] },
          "o": { "a": 0, "k": 60 },
          "r": 1,
          "nm": "Fill"
        }
      ],
      "ip": 0,
      "op": 120,
      "st": 0
    },
    {
      "ddd": 0,
      "ind": 3,
      "ty": 4,
      "nm": "Accent Line Top",
      "sr": 1,
      "ks": {
        "o": { "a": 1, "k": [
          { "t": 5, "s": [0], "e": [70] },
          { "t": 25, "s": [70], "e": [70] },
          { "t": 110, "s": [70], "e": [0] },
          { "t": 120, "s": [0] }
        ]},
        "r": { "a": 0, "k": -10 },
        "p": { "a": 1, "k": [
          { "t": 0, "s": [500, 300, 0], "e": [960, 300, 0] },
          { "t": 60, "s": [960, 300, 0], "e": [1400, 300, 0] },
          { "t": 120, "s": [1400, 300, 0] }
        ]},
        "a": { "a": 0, "k": [0, 0, 0] },
        "s": { "a": 1, "k": [
          { "t": 5, "s": [0, 100, 100], "e": [100, 100, 100] },
          { "t": 35, "s": [100, 100, 100] }
        ]}
      },
      "ao": 0,
      "shapes": [
        {
          "ty": "rc",
          "d": 1,
          "s": { "a": 0, "k": [700, 3] },
          "p": { "a": 0, "k": [0, 0] },
          "r": { "a": 0, "k": 2 },
          "nm": "Line"
        },
        {
          "ty": "fl",
          "c": { "a": 0, "k": [0.984, 0.69, 0.494, 1] },
          "o": { "a": 0, "k": 100 },
          "r": 1,
          "nm": "Fill"
        }
      ],
      "ip": 0,
      "op": 120,
      "st": 0
    },
    {
      "ddd": 0,
      "ind": 4,
      "ty": 4,
      "nm": "Accent Line Bottom",
      "sr": 1,
      "ks": {
        "o": { "a": 1, "k": [
          { "t": 8, "s": [0], "e": [70] },
          { "t": 28, "s": [70], "e": [70] },
          { "t": 110, "s": [70], "e": [0] },
          { "t": 120, "s": [0] }
        ]},
        "r": { "a": 0, "k": 10 },
        "p": { "a": 1, "k": [
          { "t": 0, "s": [1400, 780, 0], "e": [960, 780, 0] },
          { "t": 60, "s": [960, 780, 0], "e": [500, 780, 0] },
          { "t": 120, "s": [500, 780, 0] }
        ]},
        "a": { "a": 0, "k": [0, 0, 0] },
        "s": { "a": 1, "k": [
          { "t": 8, "s": [0, 100, 100], "e": [100, 100, 100] },
          { "t": 38, "s": [100, 100, 100] }
        ]}
      },
      "ao": 0,
      "shapes": [
        {
          "ty": "rc",
          "d": 1,
          "s": { "a": 0, "k": [700, 3] },
          "p": { "a": 0, "k": [0, 0] },
          "r": { "a": 0, "k": 2 },
          "nm": "Line"
        },
        {
          "ty": "fl",
          "c": { "a": 0, "k": [0.208, 0.506, 0.722, 1] },
          "o": { "a": 0, "k": 100 },
          "r": 1,
          "nm": "Fill"
        }
      ],
      "ip": 0,
      "op": 120,
      "st": 0
    },
    {
      "ddd": 0,
      "ind": 5,
      "ty": 4,
      "nm": "Small Triangle",
      "sr": 1,
      "ks": {
        "o": { "a": 1, "k": [
          { "t": 20, "s": [0], "e": [60] },
          { "t": 40, "s": [60], "e": [60] },
          { "t": 100, "s": [60], "e": [0] },
          { "t": 120, "s": [0] }
        ]},
        "r": { "a": 1, "k": [
          { "t": 0, "s": [0], "e": [-90] },
          { "t": 120, "s": [-90] }
        ]},
        "p": { "a": 1, "k": [
          { "t": 0, "s": [1200, 650, 0], "e": [1250, 600, 0] },
          { "t": 60, "s": [1250, 600, 0], "e": [1200, 650, 0] },
          { "t": 120, "s": [1200, 650, 0] }
        ]},
        "a": { "a": 0, "k": [0, 0, 0] },
        "s": { "a": 1, "k": [
          { "t": 20, "s": [0, 0, 100], "e": [100, 100, 100] },
          { "t": 50, "s": [100, 100, 100] }
        ]}
      },
      "ao": 0,
      "shapes": [
        {
          "ty": "sr",
          "sy": 1,
          "d": 1,
          "pt": { "a": 0, "k": 3 },
          "p": { "a": 0, "k": [0, 0] },
          "r": { "a": 0, "k": 0 },
          "or": { "a": 0, "k": 50 },
          "os": { "a": 0, "k": 0 },
          "ix": 1,
          "nm": "Triangle"
        },
        {
          "ty": "fl",
          "c": { "a": 0, "k": [0.984, 0.69, 0.494, 0.5] },
          "o": { "a": 0, "k": 100 },
          "r": 1,
          "nm": "Fill"
        },
        {
          "ty": "st",
          "c": { "a": 0, "k": [0.984, 0.69, 0.494, 1] },
          "o": { "a": 0, "k": 60 },
          "w": { "a": 0, "k": 2 },
          "lc": 2,
          "lj": 2,
          "nm": "Stroke"
        }
      ],
      "ip": 0,
      "op": 120,
      "st": 0
    },
    {
      "ddd": 0,
      "ind": 6,
      "ty": 4,
      "nm": "Dot Grid",
      "sr": 1,
      "ks": {
        "o": { "a": 1, "k": [
          { "t": 30, "s": [0], "e": [40] },
          { "t": 50, "s": [40], "e": [40] },
          { "t": 90, "s": [40], "e": [0] },
          { "t": 120, "s": [0] }
        ]},
        "r": { "a": 0, "k": 0 },
        "p": { "a": 0, "k": [300, 500, 0] },
        "a": { "a": 0, "k": [0, 0, 0] },
        "s": { "a": 1, "k": [
          { "t": 30, "s": [0, 0, 100], "e": [100, 100, 100] },
          { "t": 55, "s": [100, 100, 100] }
        ]}
      },
      "ao": 0,
      "shapes": [
        {
          "ty": "el",
          "d": 1,
          "s": { "a": 0, "k": [16, 16] },
          "p": { "a": 0, "k": [0, 0] },
          "nm": "Dot"
        },
        {
          "ty": "fl",
          "c": { "a": 0, "k": [0.208, 0.506, 0.722, 1] },
          "o": { "a": 0, "k": 100 },
          "r": 1,
          "nm": "Fill"
        }
      ],
      "ip": 0,
      "op": 120,
      "st": 0
    }
  ],
  "markers": []
}